ab_service/user/__init__.py
ab_service/user/main.py
ab_service/user/schema.py
ab_service/user/routes/__init__.py
ab_service/user/routes/user.py
ab_user_service-0.3.0.dist-info/METADATA
ab_user_service-0.3.0.dist-info/WHEEL
ab_user_service-0.3.0.dist-info/licenses/LICENSE
ab_user_service-0.3.0.dist-info/RECORD
